{
  "title": "Effective-stress coordinates bound transferable machine-learning gains in liquefaction prediction",
  "upload_type": "software",
  "description": "Reproducibility package with deterministic analysis scripts, derived outputs, provenance records, sensitivity checks, and publication figure sources for a study of effective-stress coordinate bounds and conformal decision reliability in machine-learning liquefaction prediction.",
  "creators": [
    {
      "name": "[Family name], [Given name]",
      "affiliation": "Inner Mongolia University of Technology"
    }
  ],
  "license": "MIT",
  "keywords": [
    "soil liquefaction",
    "geotechnical AI",
    "physics-informed machine learning",
    "measured improvement bound",
    "grouped validation",
    "conformal prediction",
    "operational non-inferiority"
  ],
  "related_identifiers": [
    {
      "identifier": "https://github.com/Johnsonlijian/geostructural-reliability-ai-p1",
      "relation": "isSupplementTo",
      "scheme": "url"
    }
  ]
}
